[
  {
    "p_id": 10152,
    "id": "10152_2",
    "pinyin_name_phonetic": "",
    "alias": "",
    "prescription": "桂（去粗皮）半两。",
    "making": "上为末，以鱼膏和。",
    "functional_indications": "聤耳，耳中痛，脓血出。",
    "usage": "本方方名，《普济方》引作“塞耳桂膏”。",
    "care": "",
    "excerpt": "《圣济总录》卷一一五",
    "pharmacological_action": "",
    "remark": "",
    "name": "《圣济总录》卷一一五：桂膏"
  },
  {
    "p_id": 10410,
    "id": "10410_1",
    "pinyin_name_phonetic": "",
    "alias": "",
    "prescription": "甘草3两，黄芩3两，黄连3两，芎藭3两，白芷3两，藁本3两，当归3两，附子1两。",
    "making": "上取猪脂4斤煎为膏，纳药煎3沸，至白芷黄，去滓。",
    "functional_indications": "小儿耳聋、聤耳脓血出。",
    "usage": "用枣大涂耳，敷鸡骨粉。",
    "care": "",
    "excerpt": "《幼幼新书》卷三十三引《婴孺方》",
    "pharmacological_action": "",
    "remark": "",
    "name": "《幼幼新书》卷三十三引《婴孺方》：甘草膏"
  },
  {
    "p_id": 12242,
    "id": "12242_7",
    "pinyin_name_phonetic": "",
    "alias": "",
    "prescription": "枯矾5分，黄丹5分，水龙骨（即船底老油灰）1钱（煅，研），海螵蛸。",
    "making": "上为细末。",
    "functional_indications": "聤耳流脓。",
    "usage": "方中海螵蛸用量原缺。",
    "care": "",
    "excerpt": "《医级·杂医类方》卷八",
    "pharmacological_action": "",
    "remark": "",
    "name": "《医级·杂医类方》卷八：红玉散"
  },
  {
    "p_id": 12265,
    "id": "12265_14",
    "pinyin_name_phonetic": "",
    "alias": "",
    "prescription": "信砒1钱，坯子胭脂3钱，麝香1字。",
    "making": "上为末，以柳絮滚和匀。",
    "functional_indications": "小儿聤耳，内生疮，或有脓汁。",
    "usage": "每用黄米少许，掺入耳中。如绕耳生疮，脓汁不愈者，以此敷疮上，纸片封之。",
    "care": "",
    "excerpt": "《卫生总微》卷十八",
    "pharmacological_action": "",
    "remark": "",
    "name": "《卫生总微》卷十八：红绵散"
  },
  {
    "p_id": 12265,
    "id": "12265_15",
    "pinyin_name_phonetic": "",
    "alias": "红散",
    "prescription": "枯矾2钱，胭脂半钱，炉甘石（研）2钱，麝香少许。",
    "making": "上为细末。",
    "functional_indications": "聤耳出脓及黄汁。",
    "usage": "用棉子缠缴耳中，令脓汁尽，别用绵子蘸药入耳；或干吹少许亦可。",
    "care": "",
    "excerpt": "《普济方》卷五十五",
    "pharmacological_action": "",
    "remark": "",
    "name": "《普济方》卷五十五：红绵散"
  },
  {
    "p_id": 12265,
    "id": "12265_19",
    "pinyin_name_phonetic": "",
    "alias": "",
    "prescription": "煅龙骨3钱，枯矾3钱，海螵蛸1钱，胭脂1钱（烧灰），飞丹2钱，冰片3分。",
    "making": "上为细末。",
    "functional_indications": "聤耳出脓。",
    "usage": "先以绵纸搅去脓，后吹之。",
    "care": "",
    "excerpt": "《外科方外奇方》卷四",
    "pharmacological_action": "",
    "remark": "",
    "name": "《外科方外奇方》卷四：红绵散"
  },
  {
    "p_id": 12265,
    "id": "12265_6",
    "pinyin_name_phonetic": "",
    "alias": "红棉散",
    "prescription": "海螵蛸1钱，枯矾1钱，麝香1字，干胭脂5分。",
    "making": "上为末。",
    "functional_indications": "聤耳有脓及黄水。",
    "usage": "红棉散（《医门八法》卷三）。",
    "care": "",
    "excerpt": "《丹溪心法附余》卷十二",
    "pharmacological_action": "",
    "remark": "",
    "name": "《丹溪心法附余》卷十二：红绵散"
  },
  {
    "p_id": 12281,
    "id": "12281_9",
    "pinyin_name_phonetic": "",
    "alias": "",
    "prescription": "红花1分，白矾1两（烧灰）。",
    "making": "上为细末。",
    "functional_indications": "聤耳，累年脓水不绝，臭秽。",
    "usage": "每用少许纳耳中。",
    "care": "",
    "excerpt": "方出《圣惠》卷三十六，名见《圣济总录》卷一一五",
    "pharmacological_action": "",
    "remark": "",
    "name": "方出《圣惠》卷三十六，名见《圣济总录》卷一一五：红花散"
  },
  {
    "p_id": 12302,
    "id": "12302_1",
    "pinyin_name_phonetic": "",
    "alias": "",
    "prescription": "红蓝花1两（洗，焙干），黄柏（锉）1两，乌鱼骨半两，黄芩半两（上为细末），雄黄（水磨细研）半两，麝香1分（细研）。",
    "making": "上药都拌匀。",
    "functional_indications": "小儿聤耳久不愈。",
    "usage": "本方方名，《准绳·幼科》引作“红蓝花散”。",
    "care": "",
    "excerpt": "《幼幼新书》卷三十三引张涣方",
    "pharmacological_action": "",
    "remark": "",
    "name": "《幼幼新书》卷三十三引张涣方：红蓝散"
  },
  {
    "p_id": 12460,
    "id": "12460_1",
    "pinyin_name_phonetic": "",
    "alias": "",
    "prescription": "花胭脂半两，白龙骨半两，白矾灰半两，白石脂半两。",
    "making": "上为末，枣瓤为丸，如枣核大。",
    "functional_indications": "小儿聤耳，恒出脓水，久不止者。",
    "usage": "本方原名“花胭脂散”，与剂型不符，据《幼幼新书》改。",
    "care": "",
    "excerpt": "《圣惠》卷八十九",
    "pharmacological_action": "",
    "remark": "",
    "name": "花胭指丸"
  },
  {
    "p_id": 12929,
    "id": "12929_1",
    "pinyin_name_phonetic": "",
    "alias": "",
    "prescription": "黄矾15克 乌贼鱼骨7．5克 黄连7．5克（去须）",
    "making": "上药捣罗为末。",
    "functional_indications": "治小儿聤耳，出脓水。",
    "usage": "绵裹如枣核大，塞耳中，一日换三次。",
    "care": "",
    "excerpt": "《太平圣惠方》卷八十九",
    "pharmacological_action": "",
    "remark": "",
    "name": "《太平圣惠方》卷八十九：黄矾散"
  },
  {
    "p_id": 12929,
    "id": "12929_7",
    "pinyin_name_phonetic": "",
    "alias": "",
    "prescription": "黄矾半两，乌贼鱼骨1分，黄连1分（去须）。",
    "making": "上为末。",
    "functional_indications": "小儿聤耳出脓水。",
    "usage": "绵裹如枣核大，塞耳中，日3次。",
    "care": "",
    "excerpt": "《圣惠》卷八十九",
    "pharmacological_action": "",
    "remark": "",
    "name": "《圣惠》卷八十九：黄矾散"
  },
  {
    "p_id": 12929,
    "id": "12929_8",
    "pinyin_name_phonetic": "",
    "alias": "",
    "prescription": "黄矾半两。",
    "making": "纳瓶中，火烧令汁尽，细研为散。",
    "functional_indications": "聤耳。耳卒肿出脓。",
    "usage": "绵裹1钱匕，塞耳中。",
    "care": "",
    "excerpt": "《圣济总录》卷一一五",
    "pharmacological_action": "",
    "remark": "",
    "name": "《圣济总录》卷一一五：黄矾散"
  },
  {
    "p_id": 13191,
    "id": "13191_118",
    "pinyin_name_phonetic": "",
    "alias": "",
    "prescription": "黄连（去须）半两，白蔹半两，赤石脂半两，龙骨半两，乌贼鱼骨半两。",
    "making": "上为散。",
    "functional_indications": "小儿聤耳久不愈。",
    "usage": "以绵裹如枣核大，塞耳中，湿即更易之。",
    "care": "",
    "excerpt": "《圣惠》卷八十九",
    "pharmacological_action": "",
    "remark": "",
    "name": "《圣惠》卷八十九：黄连散"
  },
  {
    "p_id": 13191,
    "id": "13191_89",
    "pinyin_name_phonetic": "",
    "alias": "",
    "prescription": "黄连（去须）半两，瓠子（干者）1分。",
    "making": "上为散。",
    "functional_indications": "聤耳出脓水。",
    "usage": "以少许掺耳中。",
    "care": "",
    "excerpt": "《圣济总录》卷一一五",
    "pharmacological_action": "",
    "remark": "",
    "name": "《圣济总录》卷一一五：黄连散"
  },
  {
    "p_id": 13755,
    "id": "13755_1",
    "pinyin_name_phonetic": "",
    "alias": "",
    "prescription": "薄荷油1两，樟脑2两，香油3两，薄荷冰5钱，黄蜡6钱。",
    "making": "先将油蜡化开，再加上药即成。",
    "functional_indications": "蝎螫蜂刺，汤泼火烧，风火牙疼，聤耳流脓，眼痒眼疼，目干模糊，暴发赤肿。",
    "usage": "以上均抹患处；眼疾，抹眼外皮。",
    "care": "眼内忌用。",
    "excerpt": "《全国中药成药处方集》（禹县方）",
    "pharmacological_action": "",
    "remark": "",
    "name": "健民薄荷油"
  },
  {
    "p_id": 1583,
    "id": "1583_38",
    "pinyin_name_phonetic": "",
    "alias": "龙黄散、白龙散",
    "prescription": "白矾灰半两，龙骨末半两，黄丹半两（微炒），麝香1分。",
    "making": "上为细末。",
    "functional_indications": "小儿聤耳，汁出不止。",
    "usage": "龙黄散（《医学纲目》卷三十九引汤氏方）。白龙散（《普济方》卷五十三引《经验良方》）。",
    "care": "勿令风入。",
    "excerpt": "《圣惠》卷八十九",
    "pharmacological_action": "",
    "remark": "",
    "name": "《圣惠》卷八十九：白矾散"
  },
  {
    "p_id": 1586,
    "id": "1586_2",
    "pinyin_name_phonetic": "",
    "alias": "",
    "prescription": "白矾灰半两，黄柏（锉）半两，乌贼鱼骨半两，龙骨半两。",
    "making": "上为细散。",
    "functional_indications": "小儿聤耳有脓血，疼痛不止。",
    "usage": "以绵缠柳杖，展去脓血尽，干掺药末于耳内，日2-3次。",
    "care": "",
    "excerpt": "《圣惠》卷八十九",
    "pharmacological_action": "",
    "remark": "",
    "name": "《圣惠》卷八十九：白矾灰散"
  },
  {
    "p_id": 16108,
    "id": "16108_1",
    "pinyin_name_phonetic": "",
    "alias": "",
    "prescription": "竹箭内蛀虫粪屑2钱，坯子胭脂2钱，凌霄花（干者）2钱，海螵蛸2钱，麝香1字（研，后入）。",
    "making": "上为细末。",
    "functional_indications": "小儿聤耳内生疮，或有脓汁。",
    "usage": "每用时，先以绵拈子搌耳中脓尽，乃以纸拈蘸药入耳中，日3次。",
    "care": "",
    "excerpt": "《卫生总微》卷十八",
    "pharmacological_action": "",
    "remark": "",
    "name": "箭蚛散"
  },
  {
    "p_id": 1698,
    "id": "1698_14",
    "pinyin_name_phonetic": "",
    "alias": "",
    "prescription": "白蔹1分，黄连（去须）1分，龙骨1分，乌贼鱼骨1分，赤石脂1分。",
    "making": "上为细散。",
    "functional_indications": "聤耳，出脓血不止。",
    "usage": "每用1钱，绵裹塞耳中。",
    "care": "",
    "excerpt": "方出《圣惠》卷三十六，名见《圣济总录》卷一一五",
    "pharmacological_action": "",
    "remark": "",
    "name": "方出《圣惠》卷三十六，名见《圣济总录》卷一一五：白蔹散"
  },
  {
    "p_id": 17041,
    "id": "17041_1",
    "pinyin_name_phonetic": "",
    "alias": "",
    "prescription": "白矾半两，胭脂半两，金箔7片。",
    "making": "上为细末。",
    "functional_indications": "聤耳脓水。",
    "usage": "每用半字，掺在耳内，1日3次。",
    "care": "",
    "excerpt": "《袖珍小儿》卷七",
    "pharmacological_action": "",
    "remark": "",
    "name": "《袖珍小儿》卷七：金箔散"
  },
  {
    "p_id": 17847,
    "id": "17847_2",
    "pinyin_name_phonetic": "",
    "alias": "",
    "prescription": "枯矾 龙骨各6克 黄丹4.5克 麝香0.3克 干胭脂2.1克（如无，亦可不用）",
    "making": "上为细末。",
    "functional_indications": "治聤耳流脓。",
    "usage": "先以棉签拭去脓，后以鹅毛管盛药入于耳中。",
    "care": "",
    "excerpt": "《灵验良方汇编》卷一",
    "pharmacological_action": "",
    "remark": "",
    "name": "《灵验良方汇编》卷一：枯矾散"
  },
  {
    "p_id": 1852,
    "id": "1852_12",
    "pinyin_name_phonetic": "",
    "alias": "",
    "prescription": "寒水石4两（烧半白，研），乌贼鱼骨（研）1两，滑石（研）1两，硼砂3钱，轻粉1钱。",
    "making": "上为细末。",
    "functional_indications": "生肌止痛。主耳中卒然大痛,聤耳。",
    "usage": "每用干掺。耳中痛者，油调如糊，滴纴于耳中。",
    "care": "",
    "excerpt": "《外科精义》卷下",
    "pharmacological_action": "",
    "remark": "",
    "name": "《外科精义》卷下：白龙散"
  },
  {
    "p_id": 18802,
    "id": "18802_4",
    "pinyin_name_phonetic": "",
    "alias": "",
    "prescription": "狼牙1分，白蔹1分，竹蛀屑1分。",
    "making": "上为细末。",
    "functional_indications": "聤耳，有脓水塞耳。",
    "usage": "每用少许，纳于耳中。",
    "care": "",
    "excerpt": "方出《圣惠》卷三十六，名见《圣济总录》卷一一五",
    "pharmacological_action": "",
    "remark": "",
    "name": "方出《圣惠》卷三十六，名见《圣济总录》卷一一五：狼牙散"
  },
  {
    "p_id": 18982,
    "id": "18982_14",
    "pinyin_name_phonetic": "",
    "alias": "",
    "prescription": "硫黄（研如粉）。",
    "making": "",
    "functional_indications": "小儿聤耳。",
    "usage": "上药频频掺在耳中。",
    "care": "",
    "excerpt": "《鸡峰》卷二十四",
    "pharmacological_action": "",
    "remark": "",
    "name": "《鸡峰》卷二十四：硫黄散"
  },
  {
    "p_id": 19034,
    "id": "19034_13",
    "pinyin_name_phonetic": "",
    "alias": "",
    "prescription": "真陈橘皮（灯上烧黑，为末）3克 麝香少许（别研）",
    "making": "上二味，和匀。",
    "functional_indications": "治聤耳底耳，有脓不止。",
    "usage": "每用少许，先用绵蘸耳内，脓净上药。",
    "care": "",
    "excerpt": "《重订严氏济生方》",
    "pharmacological_action": "",
    "remark": "",
    "name": "《重订严氏济生方》：立效散"
  },
  {
    "p_id": 19034,
    "id": "19034_57",
    "pinyin_name_phonetic": "",
    "alias": "",
    "prescription": "真陈橘皮（灯上烧黑，为末）1钱，麝香少许（别研）。",
    "making": "上药和匀。",
    "functional_indications": "聤耳、底耳，有脓不止。",
    "usage": "每用少许，先用绵蘸耳内，脓净上药。",
    "care": "",
    "excerpt": "《医方类聚》卷七十八引《济生》",
    "pharmacological_action": "",
    "remark": "",
    "name": "《医方类聚》卷七十八引《济生》：立效散"
  },
  {
    "p_id": 19410,
    "id": "19410_1",
    "pinyin_name_phonetic": "",
    "alias": "",
    "prescription": "红蓝花1两（洗，焙干），黄柏1两（锉），乌鱼骨半两，黄芩半两（以上为末），雄黄半两（研，水飞），麝香1分（研）。",
    "making": "上拌匀。",
    "functional_indications": "小儿聤耳内生疮，或有脓汁。",
    "usage": "每用少许，以新绵子缠捻子温药塞耳中，1日二易。",
    "care": "",
    "excerpt": "《卫生总微》卷十八",
    "pharmacological_action": "",
    "remark": "",
    "name": "蓝花散"
  },
  {
    "p_id": 19997,
    "id": "19997_1",
    "pinyin_name_phonetic": "",
    "alias": "",
    "prescription": "密陀僧 白矾（烧）夜明砂（微炒）各0.3克",
    "making": "上研细末。",
    "functional_indications": "治小儿聤耳。",
    "usage": "每用少许，干掺。",
    "care": "",
    "excerpt": "《普济方》卷三六四",
    "pharmacological_action": "",
    "remark": "",
    "name": "《普济方》卷三六四：密陀僧散"
  },
  {
    "p_id": 19998,
    "id": "19998_1",
    "pinyin_name_phonetic": "",
    "alias": "",
    "prescription": "密陀僧 白矾（烧）夜明砂（微炒）各0.3克",
    "making": "上研细末。",
    "functional_indications": "治小儿聤耳。",
    "usage": "每用少许，干掺。",
    "care": "",
    "excerpt": "《普济方》卷三六四",
    "pharmacological_action": "",
    "remark": "",
    "name": "《普济方》卷三六四：密陀僧散"
  },
  {
    "p_id": 20212,
    "id": "20212_2",
    "pinyin_name_phonetic": "",
    "alias": "",
    "prescription": "蔓荆子1钱，粉干葛1钱，赤芍药1钱，信前胡1钱，桑白皮1钱，淮木通1钱，怀生地1钱，杭麦冬1钱，赤茯苓1钱，绿升麻5分，小甘草5分。",
    "making": "",
    "functional_indications": "小儿肾气上冲，灌为聤耳。",
    "usage": "加灯心10茎，水煎服。",
    "care": "",
    "excerpt": "《幼幼集成》卷四",
    "pharmacological_action": "",
    "remark": "",
    "name": "《幼幼集成》卷四：蔓荆子散"
  },
  {
    "p_id": 22954,
    "id": "22954_1",
    "pinyin_name_phonetic": "",
    "alias": "",
    "prescription": "矾石、乌贼鱼骨、黄连、龙骨。",
    "making": "上为末。",
    "functional_indications": "聤耳脓水不断者。",
    "usage": "以枣核许绵裹塞耳中，日2次。",
    "care": "",
    "excerpt": "《外台》卷二十二引《集验良方》",
    "pharmacological_action": "",
    "remark": "",
    "name": "聤耳出脓水散"
  },
  {
    "p_id": 22955,
    "id": "22955_1",
    "pinyin_name_phonetic": "",
    "alias": "",
    "prescription": "石首鱼枕骨2两（炙），胭脂1钱（炙），冰片3钱。",
    "making": "共研匀细。",
    "functional_indications": "小儿聤耳流脓。",
    "usage": "吹耳内。",
    "care": "",
    "excerpt": "《疡科遗编》卷下",
    "pharmacological_action": "",
    "remark": "",
    "name": "《疡科遗编》卷下：聤耳散"
  },
  {
    "p_id": 22956,
    "id": "22956_1",
    "pinyin_name_phonetic": "",
    "alias": "",
    "prescription": "龙骨3钱，枯矾3钱，黄丹2钱，元寸2分。",
    "making": "上各为细末。",
    "functional_indications": "聤耳流脓。",
    "usage": "先以核桃肉打油滴入，绵花卷净，后入本药，再滴核桃油2滴。",
    "care": "",
    "excerpt": "《疡科纲要》卷下",
    "pharmacological_action": "",
    "remark": "",
    "name": "聤耳流脓药"
  },
  {
    "p_id": 4084,
    "id": "4084_13",
    "pinyin_name_phonetic": "",
    "alias": "",
    "prescription": "磁石1分（烧令赤，醋淬7遍，研），龙骨1分，白矾灰1分。",
    "making": "上为散，以生地黄汁和，捻如枣核大。",
    "functional_indications": "聤耳。通耳脓水出，日夜不止。",
    "usage": "绵裹1丸塞耳中，日3次易之。",
    "care": "",
    "excerpt": "方出《圣惠》卷三十六，名见《普济方》卷五十五",
    "pharmacological_action": "",
    "remark": "",
    "name": "方出《圣惠》卷三十六，名见《普济方》卷五十五：磁石散"
  },
  {
    "p_id": 4406,
    "id": "4406_25",
    "pinyin_name_phonetic": "",
    "alias": "",
    "prescription": "菖蒲（锉，焙）、桂（去粗皮）、野葛各等分。",
    "making": "上为散，以雀脑髓和，绵裹，如枣核大。",
    "functional_indications": "聤耳。",
    "usage": "先灸耳中宛宛者7壮，后用药塞耳中；1日1易。",
    "care": "",
    "excerpt": "《圣济总录》卷一一五",
    "pharmacological_action": "",
    "remark": "",
    "name": "《圣济总录》卷一一五：菖蒲散"
  },
  {
    "p_id": 4416,
    "id": "4416_1",
    "pinyin_name_phonetic": "",
    "alias": "菖蒲散",
    "prescription": "菖蒲1两，狼毒1两，附子（炮）1两，磁石（烧）1两，矾石（熬汁尽）1两。",
    "making": "上为末。",
    "functional_indications": "聤耳。痒，有脓不止。",
    "usage": "菖蒲散（《圣济总录》卷一一五）。",
    "care": "",
    "excerpt": "《外台》卷二十二引《广济方》",
    "pharmacological_action": "",
    "remark": "",
    "name": "《外台》卷二十二引《广济方》：菖蒲膏"
  },
  {
    "p_id": 4781,
    "id": "4781_1",
    "pinyin_name_phonetic": "",
    "alias": "",
    "prescription": "车辖脂。",
    "making": "",
    "functional_indications": "聤耳出脓血，百虫入耳。",
    "usage": "塞耳中，脓血出尽愈。",
    "care": "",
    "excerpt": "方出《肘后方》卷六，名见《普济方》卷五十五",
    "pharmacological_action": "",
    "remark": "",
    "name": "车脂膏"
  },
  {
    "p_id": 8671,
    "id": "8671_10",
    "pinyin_name_phonetic": "",
    "alias": "",
    "prescription": "矾石（烧令汁尽，研）1分，食盐（研）1分。",
    "making": "上各为细散。",
    "functional_indications": "聤耳出脓汁。",
    "usage": "先以纸捻子拭去脓汁令干，次以盐掺之，次又以矾石掺之，1日2次。",
    "care": "",
    "excerpt": "《圣济总录》卷一一五",
    "pharmacological_action": "",
    "remark": "",
    "name": "《圣济总录》卷一一五：矾石散"
  },
  {
    "p_id": 8671,
    "id": "8671_21",
    "pinyin_name_phonetic": "",
    "alias": "",
    "prescription": "矾石、乌贼骨、黄连、赤石脂各等分。",
    "making": "上为末。",
    "functional_indications": "聤耳出脓汁。",
    "usage": "以绵裹如枣核，纳耳中，每日3次。",
    "care": "",
    "excerpt": "方出《千金》卷六，名见《普济方》卷五十五",
    "pharmacological_action": "",
    "remark": "",
    "name": "方出《千金》卷六，名见《普济方》卷五十五：矾石散"
  },
  {
    "p_id": 8671,
    "id": "8671_8",
    "pinyin_name_phonetic": "",
    "alias": "",
    "prescription": "白矾（熬令汁枯）半两，龙骨半两，铅丹（炒）半两，麝香1分，竹蚛（末）1分。",
    "making": "上为细末。",
    "functional_indications": "小儿聤耳，汁出不止。",
    "usage": "先用绵杖子拭干耳内，以药少许掺之。",
    "care": "",
    "excerpt": "《圣济总录》卷一八一",
    "pharmacological_action": "",
    "remark": "",
    "name": "《圣济总录》卷一八一：矾石散"
  },
  {
    "p_id": 8685,
    "id": "8685_1",
    "pinyin_name_phonetic": "",
    "alias": "",
    "prescription": "白矾（熬令汁枯）1分，松脂1分，木香1分，花烟脂1分。",
    "making": "上为散。",
    "functional_indications": "聤耳，脓水不绝。",
    "usage": "每用绵拭脓后，满耳填药。",
    "care": "",
    "excerpt": "《圣济总录》卷一八一",
    "pharmacological_action": "",
    "remark": "",
    "name": "矾脂散"
  },
  {
    "p_id": 8696,
    "id": "8696_1",
    "pinyin_name_phonetic": "",
    "alias": "",
    "prescription": "白矾1两（烧灰），蛇床子1分（为末）。",
    "making": "上药相和，入麝香末五分，同研细。",
    "functional_indications": "小儿聤耳内生疮，或有脓汁。",
    "usage": "每用1字，掺入病耳。",
    "care": "",
    "excerpt": "《卫生总微》卷十八",
    "pharmacological_action": "",
    "remark": "",
    "name": "矾香散"
  },
  {
    "p_id": 9654,
    "id": "9654_1",
    "pinyin_name_phonetic": "",
    "alias": "",
    "prescription": "干胭脂、枯矾各等分。",
    "making": "上为末。",
    "functional_indications": "聤耳。",
    "usage": "先用绵杖子缠去脓，别以净绵杖引药入耳。",
    "care": "",
    "excerpt": "《医统》卷六十二",
    "pharmacological_action": "",
    "remark": "",
    "name": "干胭脂散"
  },
  {
    "p_id": 9655,
    "id": "9655_1",
    "pinyin_name_phonetic": "",
    "alias": "",
    "prescription": "干胭脂、白龙骨、白矾（煅）、白石脂（研）等分。",
    "making": "上为末，用枣肉为丸，如枣核大。",
    "functional_indications": "小儿聤耳，常出脓水不止。",
    "usage": "以绵裹1丸，纳耳中，日3换之。",
    "care": "",
    "excerpt": "《婴童百问》卷四",
    "pharmacological_action": "",
    "remark": "",
    "name": "干胭脂膏"
  }
]